visual_sonar.py
wvd_simulator.py
visual_sonar-1.0.1.dist-info/METADATA
visual_sonar-1.0.1.dist-info/WHEEL
visual_sonar-1.0.1.dist-info/entry_points.txt
visual_sonar-1.0.1.dist-info/top_level.txt
visual_sonar-1.0.1.dist-info/RECORD
