Metadata-Version: 2.4
Name: visual-sonar
Version: 1.0.1
Summary: WVD/Citrix Remote Desktop Automation using Computer Vision
Author-email: Dhiraj Das <dhirajdas.666@gmail.com>
License: MIT
Project-URL: Homepage, https://github.com/godhiraj-code/wvdautomation
Project-URL: Documentation, https://github.com/godhiraj-code/wvdautomation#readme
Project-URL: Repository, https://github.com/godhiraj-code/wvdautomation.git
Project-URL: Issues, https://github.com/godhiraj-code/wvdautomation/issues
Keywords: automation,rpa,wvd,citrix,remote-desktop,computer-vision,gui-automation,pyautogui,ocr
Classifier: Development Status :: 4 - Beta
Classifier: Environment :: Console
Classifier: Environment :: Win32 (MS Windows)
Classifier: Intended Audience :: Developers
Classifier: Intended Audience :: System Administrators
Classifier: License :: OSI Approved :: MIT License
Classifier: Operating System :: Microsoft :: Windows
Classifier: Programming Language :: Python :: 3
Classifier: Programming Language :: Python :: 3.8
Classifier: Programming Language :: Python :: 3.9
Classifier: Programming Language :: Python :: 3.10
Classifier: Programming Language :: Python :: 3.11
Classifier: Programming Language :: Python :: 3.12
Classifier: Topic :: Software Development :: Testing
Classifier: Topic :: System :: Systems Administration
Requires-Python: >=3.8
Requires-Dist: opencv-python>=4.5.0
Requires-Dist: numpy>=1.19.0
Requires-Dist: pyautogui>=0.9.50
Requires-Dist: Pillow>=8.0.0
Requires-Dist: pyscreeze>=0.1.28
Requires-Dist: pygetwindow>=0.0.9
Requires-Dist: pyperclip>=1.8.0
Provides-Extra: ocr
Requires-Dist: pytesseract>=0.3.10; extra == "ocr"
Provides-Extra: ocr-full
Requires-Dist: easyocr>=1.6.0; extra == "ocr-full"
Provides-Extra: crypto
Requires-Dist: cryptography>=3.4.0; extra == "crypto"
Provides-Extra: dev
Requires-Dist: pytest>=7.0.0; extra == "dev"
Requires-Dist: pytest-cov>=4.0.0; extra == "dev"
Provides-Extra: all
Requires-Dist: visual-sonar[crypto,dev,ocr]; extra == "all"
